odoo/addons/auto_setup_bank_account_number/__init__.py
odoo/addons/auto_setup_bank_account_number/__manifest__.py
odoo/addons/auto_setup_bank_account_number/models/__init__.py
odoo/addons/auto_setup_bank_account_number/models/res_partner_bank.py
odoo12_addon_auto_setup_bank_account_number-12.0.1.0.1.dist-info/METADATA
odoo12_addon_auto_setup_bank_account_number-12.0.1.0.1.dist-info/WHEEL
odoo12_addon_auto_setup_bank_account_number-12.0.1.0.1.dist-info/top_level.txt
odoo12_addon_auto_setup_bank_account_number-12.0.1.0.1.dist-info/RECORD
