Metadata-Version: 2.1
Name: odoo12-addon-auto-setup-bank-account-number
Version: 12.0.1.0.1
Summary: When a Res Partner Bank is created, a bank is set for it if it's empty
Home-page: https://coopdevs.org
Author: Coopdevs Treball SCCL
License: AGPL-3
Platform: UNKNOWN
Classifier: Programming Language :: Python
Classifier: Framework :: Odoo
Classifier: License :: OSI Approved :: GNU Affero General Public License v3
Requires-Python: >=3.5
Requires-Dist: odoo12-addon-base-bank-from-iban
Requires-Dist: odoo (<12.1dev,>=12.0a)
